cnab240/__init__.py
cnab240/errors.py
cnab240/ocorrencias.py
cnab240/registro.py
cnab240/tipos.py
cnab240/bancos/__init__.py
cnab240/bancos/banco_brasil/__init__.py
cnab240/bancos/banco_brasil/specs/header_arquivo.json
cnab240/bancos/banco_brasil/specs/header_lote_cobranca.json
cnab240/bancos/banco_brasil/specs/segmento_p.json
cnab240/bancos/banco_brasil/specs/segmento_q.json
cnab240/bancos/banco_brasil/specs/segmento_r.json
cnab240/bancos/banco_brasil/specs/segmento_s.json
cnab240/bancos/banco_brasil/specs/segmento_t.json
cnab240/bancos/banco_brasil/specs/segmento_u.json
cnab240/bancos/banco_brasil/specs/trailer_arquivo.json
cnab240/bancos/banco_brasil/specs/trailer_lote_cobranca.json
cnab240/bancos/bradesco/__init__.py
cnab240/bancos/bradesco/specs/header_arquivo.json
cnab240/bancos/bradesco/specs/header_lote_cobranca.json
cnab240/bancos/bradesco/specs/header_lote_extrato.json
cnab240/bancos/bradesco/specs/segmento_e.json
cnab240/bancos/bradesco/specs/segmento_p.json
cnab240/bancos/bradesco/specs/segmento_q.json
cnab240/bancos/bradesco/specs/segmento_r.json
cnab240/bancos/bradesco/specs/segmento_t.json
cnab240/bancos/bradesco/specs/segmento_u.json
cnab240/bancos/bradesco/specs/trailer_arquivo.json
cnab240/bancos/bradesco/specs/trailer_lote_cobranca.json
cnab240/bancos/bradesco/specs/trailer_lote_extrato.json
cnab240/bancos/bradescoPagFor/__init__.py
cnab240/bancos/bradescoPagFor/specs/HeaderArquivo.json
cnab240/bancos/bradescoPagFor/specs/TrailerArquivo.json
cnab240/bancos/bradescoPagFor/specs/TransacaoPagFor.json
cnab240/bancos/bradesco_cobranca_400/__init__.py
cnab240/bancos/bradesco_cobranca_400/specs/header_arquivo.json
cnab240/bancos/bradesco_cobranca_400/specs/trailer_arquivo.json
cnab240/bancos/bradesco_cobranca_400/specs/transacao_tipo_1.json
cnab240/bancos/bradesco_cobranca_retorno_400/__init__.py
cnab240/bancos/bradesco_cobranca_retorno_400/specs/header_arquivo.json
python_cnab-0.1.21.dist-info/METADATA
python_cnab-0.1.21.dist-info/RECORD
python_cnab-0.1.21.dist-info/WHEEL
python_cnab-0.1.21.dist-info/top_level.txt
